asdl_adt/__init__.py
asdl_adt/adt.py
asdl_adt/validators.py
asdl_adt-0.2.0.dist-info/METADATA
asdl_adt-0.2.0.dist-info/WHEEL
asdl_adt-0.2.0.dist-info/top_level.txt
asdl_adt-0.2.0.dist-info/RECORD
