Metadata-Version: 2.1
Name: asdl-adt
Version: 0.2.0
Summary: Compiler IR tools
Home-page: https://github.com/ChezJrk/asdl
Maintainer: Alex Reinking
Maintainer-email: alex_reinking@berkeley.edu
License: MIT License
Keywords: adt,asdl,development,compilers,ir
Classifier: Development Status :: 3 - Alpha
Classifier: License :: OSI Approved :: MIT License
Classifier: Intended Audience :: Developers
Classifier: Operating System :: OS Independent
Classifier: Topic :: Software Development :: Build Tools
Classifier: Programming Language :: Python :: 3
Classifier: Programming Language :: Python :: 3.8
Classifier: Programming Language :: Python :: 3.9
Classifier: Programming Language :: Python :: 3.10
Classifier: Programming Language :: Python :: 3.11
Classifier: Programming Language :: Python :: 3 :: Only
Requires-Dist: asdl
Requires-Dist: attrs
